fds/__init__.py
fds/sdk/__init__.py
fds/sdk/NaturalLanguageProcessing/__init__.py
fds/sdk/NaturalLanguageProcessing/api_client.py
fds/sdk/NaturalLanguageProcessing/configuration.py
fds/sdk/NaturalLanguageProcessing/exceptions.py
fds/sdk/NaturalLanguageProcessing/model_utils.py
fds/sdk/NaturalLanguageProcessing/rest.py
fds/sdk/NaturalLanguageProcessing/api/__init__.py
fds/sdk/NaturalLanguageProcessing/api/ai_text_summarization_api.py
fds/sdk/NaturalLanguageProcessing/api/ai_themes_api.py
fds/sdk/NaturalLanguageProcessing/api/named_entity_recognition_api.py
fds/sdk/NaturalLanguageProcessing/api/question__answer_api.py
fds/sdk/NaturalLanguageProcessing/apis/__init__.py
fds/sdk/NaturalLanguageProcessing/model/__init__.py
fds/sdk/NaturalLanguageProcessing/model/error.py
fds/sdk/NaturalLanguageProcessing/model/error_source.py
fds/sdk/NaturalLanguageProcessing/model/http_error.py
fds/sdk/NaturalLanguageProcessing/model/http_error_root.py
fds/sdk/NaturalLanguageProcessing/model/ner_entity.py
fds/sdk/NaturalLanguageProcessing/model/ner_entity_list.py
fds/sdk/NaturalLanguageProcessing/model/ner_input_data_schema.py
fds/sdk/NaturalLanguageProcessing/model/ner_input_schema.py
fds/sdk/NaturalLanguageProcessing/model/ner_organization.py
fds/sdk/NaturalLanguageProcessing/model/ner_response_schema.py
fds/sdk/NaturalLanguageProcessing/model/qn_a_answer.py
fds/sdk/NaturalLanguageProcessing/model/qn_a_answer_parameters.py
fds/sdk/NaturalLanguageProcessing/model/qn_a_answer_parameters_root.py
fds/sdk/NaturalLanguageProcessing/model/qn_a_answer_root.py
fds/sdk/NaturalLanguageProcessing/model/summarization_http_error.py
fds/sdk/NaturalLanguageProcessing/model/summarization_request.py
fds/sdk/NaturalLanguageProcessing/model/summarization_result.py
fds/sdk/NaturalLanguageProcessing/model/summarization_result_id.py
fds/sdk/NaturalLanguageProcessing/model/task.py
fds/sdk/NaturalLanguageProcessing/model/task_root.py
fds/sdk/NaturalLanguageProcessing/model/theme_sentiment.py
fds.sdk.NaturalLanguageProcessing-0.23.7.dist-info/LICENSE
fds.sdk.NaturalLanguageProcessing-0.23.7.dist-info/METADATA
fds.sdk.NaturalLanguageProcessing-0.23.7.dist-info/WHEEL
fds.sdk.NaturalLanguageProcessing-0.23.7.dist-info/top_level.txt
fds.sdk.NaturalLanguageProcessing-0.23.7.dist-info/RECORD
